{"ticker": "SNDK", "profile": {"ticker": "SNDK", "name": "Sandisk Corp", "sector": "Technology", "industry": "", "exchange": "NASDAQ NMS - GLOBAL MARKET", "market_cap": 206223.895246, "shares": 148.09, "logo": "https://static2.finnhub.io/file/publicdatany/finnhubimage/stock_logo/950906460416.png", "website": "https://www.sandisk.com/", "country": "US", "currency": "USD", "ipo_date": "2025-02-13", "employees": null, "description": "L\u00edder mundial en almacenamiento flash NAND y SSDs. Portfolio de productos para data centers, edge computing y consumo. Spin-off de Western Digital con foco en memoria de alta densidad.", "dividend_yield": null}, "quote": {"price": 1469.76, "change": 77.2, "pct_change": 5.54, "high": 1471.0, "low": 1377.47, "prev_close": 1392.56}, "metrics": {"pe_ttm": 50.303, "pe_forward": 8.3869, "ps_ttm": 16.5215, "pb_annual": 21.3146, "ev_ebitda_ttm": 35.99, "ev_sales_ttm": 15.374, "beta": null, "week52_high": 1600.0, "week52_low": 35.79, "eps_ttm": 29.24, "eps_forward": 175.3757, "roe_ttm": 39.3, "roa_ttm": 22.82, "roic_ttm": null, "gross_margin_ttm": 56.04, "ebitda_margin_ttm": 42.72, "net_margin_ttm": 34.19, "operating_margin_ttm": 69.98, "fcf_margin_ttm": null, "revenue_ttm_m": 13184.0, "ebitda_ttm_m": 5632.0, "fcf_ttm_m": 2259.5, "dividend_yield": null, "target_price": 1493.3636, "upside": 1.53, "recommendation": "buy", "num_analysts": 22, "enterprise_value_m": 202695.8684}, "description": "L\u00edder mundial en almacenamiento flash NAND y SSDs. Portfolio de productos para data centers, edge computing y consumo. Spin-off de Western Digital con foco en memoria de alta densidad.", "tags": ["Semiconductores", "Storage", "NAND", "Data Center"], "financials": [{"year": 2023, "end_date": "2023-06-30", "revenue": 6086.0, "gross_profit": 430.0, "operating_income": -2035.0, "net_income": -2143.0, "da": 448.0, "eps_diluted": -14.78, "cfo": -713.0, "capex": 219.0, "cash": null, "debt_lt": null, "debt_st": null, "equity": null, "total_assets": null, "total_debt": 0.0, "fcf": -932.0, "net_cash": 0.0, "ebitda_est": -1587.0, "gross_margin": 7.07, "ebit_margin": -33.44, "ebitda_margin": -26.08, "net_margin": -35.21, "fcf_margin": -15.31, "revenue_yoy": null, "net_income_yoy": null, "fcf_yoy": null, "de_ratio": null}, {"year": 2024, "end_date": "2024-06-30", "revenue": 6663.0, "gross_profit": 1072.0, "operating_income": -468.0, "net_income": -672.0, "da": 224.0, "eps_diluted": -4.63, "cfo": -309.0, "capex": 166.0, "cash": 328.0, "debt_lt": 171.0, "debt_st": 814.0, "equity": 11082.0, "total_assets": 13506.0, "total_debt": 985.0, "fcf": -475.0, "net_cash": -657.0, "ebitda_est": -244.0, "gross_margin": 16.09, "ebit_margin": -7.02, "ebitda_margin": -3.66, "net_margin": -10.09, "fcf_margin": -7.13, "revenue_yoy": 9.5, "net_income_yoy": -68.6, "fcf_yoy": -49.0, "de_ratio": 0.09}, {"year": 2025, "end_date": "2025-06-30", "revenue": 7355.0, "gross_profit": 2212.0, "operating_income": -1377.0, "net_income": -1641.0, "da": 163.0, "eps_diluted": -11.32, "cfo": 84.0, "capex": 204.0, "cash": 1481.0, "debt_lt": 2022.0, "debt_st": 20.0, "equity": 9216.0, "total_assets": 12985.0, "total_debt": 2042.0, "fcf": -120.0, "net_cash": -561.0, "ebitda_est": -1214.0, "gross_margin": 30.07, "ebit_margin": -18.72, "ebitda_margin": -16.51, "net_margin": -22.31, "fcf_margin": -1.63, "revenue_yoy": 10.4, "net_income_yoy": 144.2, "fcf_yoy": -74.7, "de_ratio": 0.22, "rev_cagr_3y": 9.9}], "candles": {"status": "ok", "dates": ["2025-02-10", "2025-02-17", "2025-02-24", "2025-03-03", "2025-03-10", "2025-03-17", "2025-03-24", "2025-03-31", "2025-04-07", "2025-04-14", "2025-04-21", "2025-04-28", "2025-05-05", "2025-05-12", "2025-05-19", "2025-05-26", "2025-06-02", "2025-06-09", "2025-06-16", "2025-06-23", "2025-06-30", "2025-07-07", "2025-07-14", "2025-07-21", "2025-07-28", "2025-08-04", "2025-08-11", "2025-08-18", "2025-08-25", "2025-09-01", "2025-09-08", "2025-09-15", "2025-09-22", "2025-09-29", "2025-10-06", "2025-10-13", "2025-10-20", "2025-10-27", "2025-11-03", "2025-11-10", "2025-11-17", "2025-11-24", "2025-12-01", "2025-12-08", "2025-12-15", "2025-12-22", "2025-12-29", "2026-01-05", "2026-01-12", "2026-01-19", "2026-01-26", "2026-02-02", "2026-02-09", "2026-02-16", "2026-02-23", "2026-03-02", "2026-03-09", "2026-03-16", "2026-03-23", "2026-03-30", "2026-04-06", "2026-04-13", "2026-04-20", "2026-04-27", "2026-05-04", "2026-05-11", "2026-05-18"], "closes": [36.65, 50.37, 46.85, 51.0, 54.82, 53.96, 48.97, 30.11, 31.97, 31.29, 32.85, 34.4, 37.74, 40.44, 37.28, 37.69, 39.15, 42.5, 46.58, 47.15, 46.41, 46.09, 42.19, 42.48, 41.33, 44.34, 44.54, 46.37, 52.47, 68.55, 86.13, 102.21, 97.12, 128.41, 116.91, 140.16, 186.16, 199.33, 239.48, 254.16, 200.27, 223.28, 228.47, 206.18, 237.61, 250.05, 275.24, 377.41, 413.62, 473.83, 576.25, 597.95, 626.56, 649.97, 635.36, 527.33, 661.62, 709.71, 615.83, 701.59, 851.77, 920.99, 989.9, 1187.0, 1562.34, 1407.61, 1472.01]}, "generated_at": "2026-05-21T13:59:40.997942"}